copilot/__init__.py
copilot/client.js
copilot/context_extractor.py
copilot/copilot.py
copilot/copilot_models.py
copilot/node_modules/.yarn-integrity
copilot/node_modules/.bin/copilot-node-server
copilot/node_modules/.bin/mime
copilot/node_modules/accepts/HISTORY.md
copilot/node_modules/accepts/LICENSE
copilot/node_modules/accepts/README.md
copilot/node_modules/accepts/index.js
copilot/node_modules/accepts/package.json
copilot/node_modules/array-flatten/LICENSE
copilot/node_modules/array-flatten/README.md
copilot/node_modules/array-flatten/array-flatten.js
copilot/node_modules/array-flatten/package.json
copilot/node_modules/body-parser/HISTORY.md
copilot/node_modules/body-parser/LICENSE
copilot/node_modules/body-parser/README.md
copilot/node_modules/body-parser/SECURITY.md
copilot/node_modules/body-parser/index.js
copilot/node_modules/body-parser/package.json
copilot/node_modules/body-parser/lib/read.js
copilot/node_modules/body-parser/lib/types/json.js
copilot/node_modules/body-parser/lib/types/raw.js
copilot/node_modules/body-parser/lib/types/text.js
copilot/node_modules/body-parser/lib/types/urlencoded.js
copilot/node_modules/bytes/History.md
copilot/node_modules/bytes/LICENSE
copilot/node_modules/bytes/Readme.md
copilot/node_modules/bytes/index.js
copilot/node_modules/bytes/package.json
copilot/node_modules/call-bind-apply-helpers/.eslintrc
copilot/node_modules/call-bind-apply-helpers/.nycrc
copilot/node_modules/call-bind-apply-helpers/CHANGELOG.md
copilot/node_modules/call-bind-apply-helpers/LICENSE
copilot/node_modules/call-bind-apply-helpers/README.md
copilot/node_modules/call-bind-apply-helpers/actualApply.d.ts
copilot/node_modules/call-bind-apply-helpers/actualApply.js
copilot/node_modules/call-bind-apply-helpers/applyBind.d.ts
copilot/node_modules/call-bind-apply-helpers/applyBind.js
copilot/node_modules/call-bind-apply-helpers/functionApply.d.ts
copilot/node_modules/call-bind-apply-helpers/functionApply.js
zero_true-0.6.0.dist-info/LICENSE
zero_true-0.6.0.dist-info/METADATA
zero_true-0.6.0.dist-info/WHEEL
zero_true-0.6.0.dist-info/entry_points.txt
zero_true-0.6.0.dist-info/top_level.txt
zero_true-0.6.0.dist-info/RECORD
