Metadata-Version: 2.2
Name: zero-true
Version: 0.6.0
Summary: A collaborative notebook built for data scientists
Home-page: https://zero-true.com
Author: Zero-True
Author-email: support@zero-true.com
License: Apache License 2.0
Requires-Python: >=3.9
License-File: LICENSE
Requires-Dist: fastapi<=0.115.6
Requires-Dist: uvicorn[standard]<=0.34.0
Requires-Dist: pydantic==2.10.5
Requires-Dist: astroid<=3.3.8
Requires-Dist: duckdb<=1.1.3
Requires-Dist: pydantic-settings<=2.7.1
Requires-Dist: typer<=0.15.1
Requires-Dist: rich<=13.9.4
Requires-Dist: requests<=2.32.3
Requires-Dist: rtoml==0.12.0
Requires-Dist: jedi<=0.19.2
Requires-Dist: python-multipart<=0.0.20
Requires-Dist: ruff<=0.9.0
Provides-Extra: test
Requires-Dist: pytest==8.3.4; extra == "test"
Requires-Dist: selenium==4.27.1; extra == "test"
Requires-Dist: pandas<=2.2.3; extra == "test"
Provides-Extra: components
Requires-Dist: pandas<=2.2.3; extra == "components"
Requires-Dist: plotly<=5.24.1; extra == "components"
Requires-Dist: pygwalker<=0.4.9.13; extra == "components"
Requires-Dist: openai<=1.59.5; extra == "components"
Requires-Dist: matplotlib<=3.9.4; extra == "components"
